xlang/__init__.py
xlang/__main__.py
xlang/__test__.py
xlang/ir/IR.py
xlang/ir/__init__.py
xlang/ir/context.py
xlang/ir/variable.py
xlang/parser/IR_generator.py
xlang/parser/__init__.py
xlang/parser/ast.py
xlang/parser/lexer.py
xlang/xlang/__init__.py
xlang/xlang/cli.py
xlang/xlang/lang.py
xlang_script-0.1.1.post0.dist-info/LICENSE
xlang_script-0.1.1.post0.dist-info/METADATA
xlang_script-0.1.1.post0.dist-info/WHEEL
xlang_script-0.1.1.post0.dist-info/entry_points.txt
xlang_script-0.1.1.post0.dist-info/top_level.txt
xlang_script-0.1.1.post0.dist-info/RECORD
