Metadata-Version: 2.1
Name: xlang-script
Version: 0.1.1.post0
Summary: XLang - Lightweight programming language
Home-page: https://github.com/sjrsjz/XLang
Author: sjrsjz@github
Author-email: sjrsjz@gmail.com
Project-URL: Source, https://github.com/sjrsjz/XLang
Keywords: programming language,interpreter,compiler
Classifier: Development Status :: 3 - Alpha
Classifier: Intended Audience :: Developers
Classifier: License :: OSI Approved :: MIT License
Classifier: Programming Language :: Python :: 3
Classifier: Programming Language :: Python :: 3.7
Classifier: Programming Language :: Python :: 3.8
Classifier: Programming Language :: Python :: 3.9
Classifier: Programming Language :: Python :: 3.10
Requires-Python: >=3.7
License-File: LICENSE
Requires-Dist: prompt-toolkit>=3.0.0
